{
  "Voice Name": "ORGAN X-PLANT",
  "Op1 Envelope Time 1": 15,
  "Op1 Envelope Time 2": 74,
  "Op1 Envelope Time 3": 74,
  "Op1 Envelope Time 4": 54,
  "Op1 Envelope Level 2": 93,
  "Op1 Envelope Level 3": 90,
  "Op2 Envelope Time 1": 13,
  "Op2 Envelope Time 2": 74,
  "Op2 Envelope Time 3": 74,
  "Op2 Envelope Time 4": 54,
  "Op2 Envelope Level 2": 93,
  "Op2 Envelope Level 3": 83,
  "Op2 Frequency": 1.495,
  "Op2 Total Output Level": 91,
  "Op2 Velocity Sensitivity": 1,
  "Op3 Envelope Time 1": 12,
  "Op3 Envelope Time 2": 64,
  "Op3 Envelope Time 3": 74,
  "Op3 Envelope Time 4": 74,
  "Op3 Envelope Level 2": 64,
  "Op3 Envelope Level 3": 44,
  "Op3 Frequency": 3.0,
  "Op3 Total Output Level": 55,
  "Op4 Envelope Time 1": 15,
  "Op4 Envelope Time 2": 54,
  "Op4 Envelope Time 3": 82,
  "Op4 Envelope Time 4": 54,
  "Op4 Envelope Level 2": 92,
  "Op4 Envelope Level 3": 68,
  "Op4 Frequency": 0.25,
  "Op4 Total Output Level": 99,
  "Op4 Velocity Sensitivity": 3,
  "Op5 Envelope Time 1": 12,
  "Op5 Envelope Time 2": 74,
  "Op5 Envelope Level 2": 0,
  "Op5 Envelope Level 3": 0,
  "Op5 Frequency": 1.006,
  "Op5 Total Output Level": 63,
  "Op5 Velocity Sensitivity": 1,
  "Op6 Envelope Time 1": 12,
  "Op6 Envelope Time 2": 44,
  "Op6 Envelope Time 3": 44,
  "Op6 Envelope Level 2": 65,
  "Op6 Envelope Level 3": 0,
  "Op6 Frequency": 0.499,
  "Op6 Total Output Level": 75,
  "Algorithm": 22,
  "Feedback": 7
}
